{
  "likes": [
    {
      "id": "0",
      "likes": 0
    },
    {
      "id": "232",
      "likes": 7
    },
    {
      "id": "141",
      "likes": 2
    },
    {
      "id": "146",
      "likes": 5
    },
    {
      "id": "206",
      "likes": 8
    },
    {
      "id": "198",
      "likes": -2
    },
    {
      "id": "147",
      "likes": -1
    },
    {
      "id": "293",
      "likes": -1
    },
    {
      "id": "234",
      "likes": -1
    },
    {
      "id": "285",
      "likes": 1
    },
    {
      "id": "11",
      "likes": 1
    },
    {
      "id": "76",
      "likes": -1
    }
  ],
  "comments": [
    {
      "id": 0,
      "comments": "NaN"
    }
  ]
}